Metadata-Version: 2.1
Name: simplyfile
Version: 0.0.1
Summary: Simple file functions
Home-page: UNKNOWN
Author: Surya Teja Pallapu
Author-email: spallapu2@gitam.in
License: MIT
Keywords: simplyfile
Platform: UNKNOWN
Classifier: Development Status :: 5 - Production/Stable
Classifier: Intended Audience :: Education
Classifier: Operating System :: Microsoft :: Windows :: Windows 10
Classifier: License :: OSI Approved :: MIT License
Classifier: Programming Language :: Python :: 3
License-File: LICENCE.txt
